service_stats/__init__.py
service_stats/app.py
service_stats/slack.py
service_stats/stats/__init__.py
service_stats/stats/boot_time.py
service_stats/stats/cpu.py
service_stats/stats/disk.py
service_stats/stats/globals.py
service_stats/stats/memory.py
service_stats/stats/network.py
service_stats/stats/system.py
test/__init__.py
test/unit/__init__.py
test/unit/test_app.py
test/unit/test_boot.py
test/unit/test_cpu.py
test/unit/test_disk.py
test/unit/test_globals.py
test/unit/test_memory.py
test/unit/test_network.py
test/unit/test_slack.py
test/unit/test_system.py
service_stats-2.1.0.dist-info/LICENSE
service_stats-2.1.0.dist-info/METADATA
service_stats-2.1.0.dist-info/WHEEL
service_stats-2.1.0.dist-info/entry_points.txt
service_stats-2.1.0.dist-info/top_level.txt
service_stats-2.1.0.dist-info/RECORD
