Metadata-Version: 2.1
Name: service-stats
Version: 2.1.0
Summary: Service serves savvy server stats.
Home-page: http://github.com/justintime50/service-stats
Author: Justintime50
License: MIT
Platform: UNKNOWN
Classifier: Programming Language :: Python :: 3
Classifier: License :: OSI Approved :: MIT License
Classifier: Operating System :: OS Independent
Requires-Python: >=3.6
License-File: LICENSE
Requires-Dist: psutil (==5.*)
Requires-Dist: slackclient (==2.*)
Requires-Dist: python-dotenv (==0.17.*)
Provides-Extra: dev
Requires-Dist: coveralls (==3.*) ; extra == 'dev'
Requires-Dist: flake8 ; extra == 'dev'
Requires-Dist: mock (==4.*) ; extra == 'dev'
Requires-Dist: pytest (==6.*) ; extra == 'dev'
Requires-Dist: pytest-cov (==2.*) ; extra == 'dev'
